setup.cfg
setup.py
chainpoint/__init__.py
chainpoint/chainpoint.py
chainpoint/merkletools.py
chainpoint.egg-info/PKG-INFO
chainpoint.egg-info/SOURCES.txt
chainpoint.egg-info/dependency_links.txt
chainpoint.egg-info/not-zip-safe
chainpoint.egg-info/requires.txt
chainpoint.egg-info/top_level.txt
chainpoint/tests/__init__.py
chainpoint/tests/chainpoint_test.py